cerberus_ac/__init__.py
cerberus_ac/admin.py
cerberus_ac/apps.py
cerberus_ac/genida.rdf
cerberus_ac/models.py
cerberus_ac/plugins.py
cerberus_ac/urls.py
cerberus_ac/utils.py
cerberus_ac/views.py
cerberus_ac/migrations/0001_initial.py
cerberus_ac/migrations/0002_auto_20170515_0413.py
cerberus_ac/migrations/__init__.py
cerberus_ac/static/cerberus_ac/css/bootstrap-combined.min.css
cerberus_ac/static/cerberus_ac/css/edit_privileges.css
cerberus_ac/static/cerberus_ac/d3/.bower.json
cerberus_ac/static/cerberus_ac/d3/d3.min.js
cerberus_ac/static/cerberus_ac/datatables/datatables.css
cerberus_ac/static/cerberus_ac/datatables/datatables.js
cerberus_ac/static/cerberus_ac/datatables/datatables.min.css
cerberus_ac/static/cerberus_ac/datatables/datatables.min.js
cerberus_ac/static/cerberus_ac/datatables/Buttons-1.2.4/css/buttons.bootstrap.css
cerberus_ac/static/cerberus_ac/datatables/Buttons-1.2.4/css/buttons.bootstrap.min.css
cerberus_ac/static/cerberus_ac/datatables/Buttons-1.2.4/css/buttons.dataTables.css
cerberus_ac/static/cerberus_ac/datatables/Buttons-1.2.4/css/buttons.dataTables.min.css
cerberus_ac/static/cerberus_ac/datatables/Buttons-1.2.4/css/buttons.foundation.css
cerberus_ac/static/cerberus_ac/datatables/Buttons-1.2.4/css/buttons.foundation.min.css
cerberus_ac/static/cerberus_ac/datatables/Buttons-1.2.4/css/buttons.jqueryui.css
cerberus_ac/static/cerberus_ac/datatables/Buttons-1.2.4/css/buttons.jqueryui.min.css
cerberus_ac/static/cerberus_ac/datatables/Buttons-1.2.4/css/buttons.semanticui.css
cerberus_ac/static/cerberus_ac/datatables/Buttons-1.2.4/css/buttons.semanticui.min.css
cerberus_ac/static/cerberus_ac/datatables/Buttons-1.2.4/css/common.scss
cerberus_ac/static/cerberus_ac/datatables/Buttons-1.2.4/css/mixins.scss
cerberus_ac/static/cerberus_ac/datatables/Buttons-1.2.4/js/buttons.bootstrap.js
cerberus_ac/static/cerberus_ac/datatables/Buttons-1.2.4/js/buttons.bootstrap.min.js
django_cerberus_ac-0.2.5.dist-info/METADATA
django_cerberus_ac-0.2.5.dist-info/RECORD
django_cerberus_ac-0.2.5.dist-info/WHEEL
django_cerberus_ac-0.2.5.dist-info/entry_points.txt
django_cerberus_ac-0.2.5.dist-info/top_level.txt
