Metadata-Version: 2.1
Name: django-cerberus-ac
Version: 0.2.5
Summary: Django Ontology Based Access Control Module
Home-page: https://github.com/Genida/django-cerberus-ac
Author: Mihnea Gheorghiu
Author-email: mikigi92@gmail.com
License: ISC
Keywords: django-cerberus-ac,access control,ontology-based,least privilege,role based access control,django access control
Platform: UNKNOWN
Classifier: Development Status :: 3 - Alpha
Classifier: Intended Audience :: Developers
Classifier: Intended Audience :: Science/Research
Classifier: License :: OSI Approved :: ISC License (ISCL)
Classifier: Operating System :: Unix
Classifier: Framework :: Django
Classifier: Framework :: Django :: 1.8
Classifier: Framework :: Django :: 1.9
Classifier: Programming Language :: Python
Classifier: Programming Language :: Python :: 2.7
Classifier: Programming Language :: Python :: 3
Classifier: Programming Language :: Python :: 3.4
Classifier: Programming Language :: Python :: 3.5
Classifier: Programming Language :: Python :: 3.6
Classifier: Programming Language :: Python :: Implementation :: PyPy
Classifier: Topic :: Utilities
Requires-Dist: django-app-settings
Requires-Dist: django-suit-dashboard
